CHANGELOG.md
LICENSE
README.md
bumpr/__about__.py
bumpr/__init__.py
bumpr/__main__.py
bumpr/config.py
bumpr/helpers.py
bumpr/hooks.py
bumpr/log.py
bumpr/releaser.py
bumpr/vcs.py
bumpr/version.py
bumpr-0.3.8.dist-info/entry_points.txt
bumpr-0.3.8.dist-info/LICENSE
bumpr-0.3.8.dist-info/WHEEL
bumpr-0.3.8.dist-info/METADATA
bumpr-0.3.8.dist-info/RECORD
