Metadata-Version: 2.1
Name: bumpr
Version: 0.3.8
Summary: Version bumper and Python package releaser
Home-page: https://github.com/noirbizarre/bumpr
License: LGPL
Keywords: version,bump,release,tag
Author: Axel H.
Author-email: noirbizarre@gmail.com
Requires-Python: >=3.7,<4.0
Classifier: Development Status :: 4 - Beta
Classifier: Intended Audience :: Developers
Classifier: License :: OSI Approved :: GNU Library or Lesser General Public License (LGPL)
Classifier: License :: Other/Proprietary License
Classifier: Operating System :: OS Independent
Classifier: Programming Language :: Python :: 3
Classifier: Programming Language :: Python :: 3.7
Classifier: Programming Language :: Python :: 3.8
Classifier: Programming Language :: Python :: 3.9
Classifier: Topic :: Software Development :: Build Tools
Classifier: Topic :: Software Development :: Libraries :: Python Modules
Classifier: Topic :: System :: Software Distribution
Provides-Extra: doc
Provides-Extra: lint
Provides-Extra: test
Requires-Dist: mkdocs (>=1.2.3,<2.0.0); extra == "doc"
Requires-Dist: mkdocs-include-markdown-plugin (>=3.2.3,<4.0.0); extra == "doc"
Requires-Dist: mkdocs-material (>=7.3.5,<8.0.0); extra == "doc"
Requires-Dist: mkdocstrings (>=0.16.2,<0.17.0); extra == "doc"
Project-URL: Bug Tracker, https://github.com/noirbizarre/bumpr/issues
Project-URL: Documentation, https://bumpr.readthedocs.io/en/stable/
Project-URL: Repository, https://github.com/noirbizarre/bumpr
